[
    {
        "0": "╚",
        "1": "blank",
        "10": "blank",
        "11": "blank",
        "12": "blank",
        "13": "blank",
        "14": "blank",
        "15": "╩",
        "16": "blank",
        "17": "blank",
        "18": "╦",
        "19": "╣",
        "2": "blank",
        "20": "╣",
        "21": "blank",
        "22": "╦",
        "23": "╗",
        "24": "blank",
        "25": "blank",
        "26": "blank",
        "27": "╬",
        "28": "blank",
        "29": "blank",
        "3": "╠",
        "30": "blank",
        "31": "╦",
        "32": "blank",
        "33": "blank",
        "34": "blank",
        "35": "═",
        "36": "blank",
        "37": "╗",
        "38": "╚",
        "39": "blank",
        "4": "blank",
        "5": "blank",
        "6": "blank",
        "7": "blank",
        "8": "blank",
        "9": "═"
    }
]
